{
  "name": "Catoblepas",
  "slug_name": "catoblepas",
  "tags": [
    "large",
    "monstrosity",
    "cr5",
    "volos-guide"
  ],
  "size": "Large",
  "type": "monstrosity",
  "subtype": null,
  "alignment": "unaligned",
  "armor_class": "14",
  "armor_class_type": "natural armor",
  "hit_points": "84",
  "hit_dice": "8d10+40",
  "speed": "30 ft.",
  "strength": "19",
  "strength_modifier": "+4",
  "dexterity": "12",
  "dexterity_modifier": "+1",
  "constitution": "21",
  "constitution_modifier": "+5",
  "intelligence": "3",
  "intelligence_modifier": "-4",
  "wisdom": "14",
  "wisdom_modifier": "+2",
  "charisma": "8",
  "charisma_modifier": "-1",
  "saving_throws": null,
  "skills": null,
  "damage_resistances": null,
  "damage_immunities": null,
  "damage_vulnerabilities": null,
  "condition_immunities": null,
  "senses": "darkvision 60 ft.",
  "languages": null,
  "challenge_rating": "5",
  "challenge_rating_decimal": 5.0,
  "experience": "1,800 XP",
  "special_abilities": [
    {
      "name": "Keen Smell.",
      "descriptions": [
        "The catoblepas has advantage on Wisdom (Perception) checks that rely on smell."
      ]
    },
    {
      "name": "Stench.",
      "descriptions": [
        "Any creature other than a catoblepas that starts its turn within 10 feet of the catoblepas must succeed on a DC 16 Constitution saving throw or be poisoned until the start of the creature's next turn. On a successful saving throw, the creature is immune to the stench of any catoblepas for 1 hour."
      ]
    }
  ],
  "actions": [
    {
      "name": "Tail.",
      "descriptions": [
        "Melee Weapon Attack: +7 to hit, reach 10 ft., one target. Hit: 21 (5d6+4) bludgeoning damage, and the target must succeed on a DC 16 Constitution saving throw or be stunned until the start of the catoblepas's next turn."
      ]
    },
    {
      "name": "Death Ray (Recharge 5-6).",
      "descriptions": [
        "The catoblepas targets a creature that it can see within 30 feet of it. The target must make a DC 16 Constitution saving throw, taking 36 (8d8) necrotic damage on a failed save, or half as much damage on a successful one. If the saving throw fails by 5 or more, the target instead takes 64 necrotic damage. The target dies if reduced to 0 hit points by this ray."
      ]
    }
  ]
}
