{
  "name": "Shoalar Quanderil",
  "slug_name": "shoalar-quanderil",
  "tags": [
    "medium",
    "humanoid",
    "cr4",
    "elemental-evil"
  ],
  "size": "Medium",
  "type": "humanoid",
  "subtype": "water genasi",
  "alignment": "lawful evil",
  "armor_class": "10",
  "armor_class_type": "13 with mage armor",
  "hit_points": "60",
  "hit_dice": "8d8+24",
  "speed": "30 ft., swim 30 ft.",
  "strength": "11",
  "strength_modifier": "+0",
  "dexterity": "12",
  "dexterity_modifier": "+1",
  "constitution": "16",
  "constitution_modifier": "+3",
  "intelligence": "14",
  "intelligence_modifier": "+2",
  "wisdom": "10",
  "wisdom_modifier": "+0",
  "charisma": "17",
  "charisma_modifier": "+3",
  "saving_throws": null,
  "skills": "Arcana +4, Deception +5, Insight +2, Persuasion +5",
  "damage_resistances": "acid",
  "damage_immunities": null,
  "damage_vulnerabilities": null,
  "condition_immunities": null,
  "senses": null,
  "languages": "Aquan, Common",
  "challenge_rating": "4",
  "challenge_rating_decimal": 4.0,
  "experience": "1,100 XP",
  "special_abilities": [
    {
      "name": "Amphibious.",
      "descriptions": [
        "Shoalar can breathe air and water."
      ]
    },
    {
      "name": "Innate Spellcasting.",
      "descriptions": [
        "Shoalar's innate spellcasting ability is Constitution (spell save DC 13, +5 to hit with spell attacks). He can innately cast the following spells: ",
        {
          "raw": "* At will: shape water",
          "hyperlinked": "* At will: <a href=\"/spell/shape-water\">shape water</a>"
        },
        {
          "raw": "* 1/day: create or destroy water",
          "hyperlinked": "* 1/day: <a href=\"/spell/create-or-destroy-water\">create or destroy water</a>"
        }
      ]
    },
    {
      "name": "Spellcasting.",
      "descriptions": [
        "Shoalar is a 5th-level spellcaster. His spellcasting ability is Charisma (spell save DC 13, +5 to hit with spell attacks). He knows the following sorcerer spells: ",
        {
          "raw": "Cantrips (at will): acid splash, chill touch, friends, prestidigitation, ray of frost",
          "hyperlinked": "Cantrips (at will): <a href=\"/spell/acid-splash\">acid splash</a>, <a href=\"/spell/chill-touch\">chill touch</a>, <a href=\"/spell/friends\">friends</a>, <a href=\"/spell/prestidigitation\">prestidigitation</a>, <a href=\"/spell/ray-of-frost\">ray of frost</a>"
        },
        {
          "raw": "1st level (4 slots): disguise self, mage armor, magic missile",
          "hyperlinked": "1st level (4 slots): <a href=\"/spell/disguise-self\">disguise self</a>, <a href=\"/spell/mage-armor\">mage armor</a>, <a href=\"/spell/magic-missile\">magic missile</a>"
        },
        {
          "raw": "2nd level (3 slots): hold person, misty step",
          "hyperlinked": "2nd level (3 slots): <a href=\"/spell/hold-person\">hold person</a>, <a href=\"/spell/misty-step\">misty step</a>"
        },
        {
          "raw": "3rd level (2 slots): tidal wave",
          "hyperlinked": "3rd level (2 slots): <a href=\"/spell/tidal-wave\">tidal wave</a>"
        }
      ]
    }
  ],
  "actions": [
    {
      "name": "Dagger.",
      "descriptions": [
        "Melee or Ranged Weapon Attack: +3 to hit, reach 5 ft. or ranged 20/60 ft., one target. Hit: 3 (1d4 + 1) piercing damage."
      ]
    }
  ]
}
